kimtrace/__init__.py
kimtrace/krun.py
kimtrace/kstep.py
kimtrace/client/__init__.py
kimtrace/client/sqs_client.py
kimtrace/helper/__init__.py
kimtrace/helper/json_formatter.py
kimtrace/helper/krun_data.py
kimtrace/helper/serializer.py
kimtrace/helper/tag_extractor.py
kimtrace/storage/__init__.py
kimtrace/storage/context_vars.py
kimtrace/types/__init__.py
kimtrace/types/external.py
kimtrace/types/internal.py
kimtrace-0.1.0.dist-info/METADATA
kimtrace-0.1.0.dist-info/WHEEL
kimtrace-0.1.0.dist-info/RECORD
