Metadata-Version: 2.4
Name: kimtrace
Version: 0.1.0
Summary: Visualize your debugging process with KimTrace
Project-URL: Homepage, https://kimtrace.dev
Project-URL: Repository, https://github.com/kimtrace/kimtrace-py
Author: KimTrace
Requires-Python: >=3.8
Requires-Dist: aioboto3>=13.4.0
Requires-Dist: aiobotocore>=2.18.0
Requires-Dist: orjson>=3.10.0
Requires-Dist: pydantic>=2.10.0
Requires-Dist: typing-extensions>=4.12.0
